drf_exception_handler/x.py
drf_exception_handler-0.0.1.dist-info/WHEEL
drf_exception_handler-0.0.1.dist-info/METADATA
drf_exception_handler-0.0.1.dist-info/RECORD
